LICENSE
weekshot_lottery_winner_selection/__init__.py
weekshot_lottery_winner_selection-0.1.3.dist-info/LICENSE
weekshot_lottery_winner_selection-0.1.3.dist-info/METADATA
weekshot_lottery_winner_selection-0.1.3.dist-info/WHEEL
weekshot_lottery_winner_selection-0.1.3.dist-info/RECORD
